{
  "project_info": {
    "project_number": "782505401266",
    "project_id": "inec-145618"
  },
  "client": [
    {
      "client_info": {
        "mobilesdk_app_id": "1:782505401266:android:cd4b3035e9b7ea9a",
        "android_client_info": {
          "package_name": "com.inec"
        }
      },
      "oauth_client": [],
      "api_key": [
        {
          "current_key": "AIzaSyAV6LGFH-axh9G2jRtF46fiTG4A92aQ8IM"
        }
      ],
      "services": {
        "analytics_service": {
          "status": 2,
          "analytics_property": {
            "tracking_id": "UA-85582094-1"
          }
        },
        "appinvite_service": {
          "status": 1,
          "other_platform_oauth_client": []
        },
        "ads_service": {
          "status": 1
        }
      }
    }
  ],
  "configuration_version": "1"
}